{
  "name": "New_v9_SpiceMarket",
  "pages": {
    "index": "SpiceMarket - Loja de especiarias online Sobre nós Vantagens Contato Avaliações +55-24-2168-8396 spicemarket@gmail.com SpiceMarket: Sabor e Qualidade Descubra uma variedade de especiarias frescas e autênticas na SpiceMarket. Deixe-se levar por aromas exóticos e sabores irresistíveis que vão transformar suas refeições em experiências únicas. SpiceMarket: Nossa História Conheça nossa jornada Em 2012, nasceu o SpiceMarket, uma ideia ousada e saborosa que se tornou realidade no coração da vibrante cultura culinária do Brasil. Fundada por apaixonados por especiarias, nossa jornada começou com o objetivo de democratizar o acesso a ingredientes de qualidade e inspirar a criatividade na cozinha. Desde então, estamos comprometidos em oferecer uma ampla variedade de especiarias autênticas, cuidadosamente selecionadas em todo o mundo. Cada produto que carregamos conta uma história, desde as montanhas do Himalaia até as plantações ensolaradas da Índia, tudo para proporcionar aos nossos clientes uma experiência gastronômica única. Ao longo dos anos, expandimos nossa linha de produtos para incluir não apenas especiarias, mas também ervas aromáticas, blends exclusivos e condimentos exóticos. Nosso compromisso com a qualidade e a autenticidade permanece inabalável, e cada etapa do nosso processo, desde a seleção dos ingredientes até a embalagem final, reflete essa paixão. Estamos orgulhosos de fazer parte da jornada culinária de nossos clientes, desde cozinheiros domésticos até chefs renomados. Junte-se a nós e embarque em uma viagem de descoberta sensorial no mundo encantador das especiarias, só no SpiceMarket. Explorando Nossas Especiarias Descubra mais Descubra as Vantagens do SpiceMarket Variedade Exclusiva Aqui no SpiceMarket, nossa variedade é incomparável. Desde os clássicos até os mais exóticos, oferecemos uma gama completa de especiarias que irão inspirar suas criações culinárias. Explore nossos corredores virtuais e descubra novos sabores para cada ocasião. Qualidade Superior Nossa dedicação à qualidade é evidente em cada aspecto do SpiceMarket. Trabalhamos diretamente com produtores e fornecedores para garantir que apenas os melhores ingredientes cheguem até você. Cada especiaria é cuidadosamente testada quanto ao sabor, aroma e frescor, para que você possa cozinhar com confiança, sabendo que está usando os melhores produtos disponíveis. Acessibilidade No SpiceMarket, acreditamos que todos devem ter acesso às melhores especiarias, independentemente do orçamento. É por isso que trabalhamos duro para manter nossos preços competitivos, sem comprometer a qualidade. Descubra como é fácil e acessível elevar suas refeições a um nível gourmet com nossos produtos. Dúvidas? Estamos aqui para ajudar! Tem alguma dúvida sobre nossos produtos ou gostaria de saber mais sobre o SpiceMarket? Estamos aqui para ajudar! Entre em contato conosco hoje mesmo e nossa equipe terá o prazer de atendê-lo. Entre em contato conosco Eu aceito Política de Privacidade Início Avaliações Política de Privacidade Termos de Uso SpiceMarket: sabor em cada grão!",
    "privacy": "SpiceMarket - Pol tica de privacidade Sobre nós Vantagens Contato Avaliações +55-24-2168-8396 spicemarket@gmail.com Política de Privacidade - SpiceMarket 1. Introdução Bem-vindo à Política de Privacidade do SpiceMarket. Nós valorizamos a privacidade de nossos usuários e entendemos a importância de proteger suas informações pessoais. Esta política descreve como coletamos, usamos, protegemos e compartilhamos suas informações ao utilizar nosso site, aplicativo móvel ou outros serviços oferecidos por nós. 2. Informações que Coletamos Podemos coletar diversas informações pessoais para fornecer e melhorar nossos serviços. Isso inclui: Informações de contato, como nome, endereço de e-mail, número de telefone; Informações de pagamento, como números de cartão de crédito; Informações demográficas, como idade, sexo, preferências de produto; Informações de uso do serviço, incluindo interações com nosso site, produtos visualizados, etc. 3. Como Usamos suas Informações Utilizamos suas informações pessoais para diversas finalidades, incluindo: Processar pedidos e transações; Fornecer suporte ao cliente; Personalizar sua experiência e recomendar produtos; Comunicar novidades, promoções e atualizações; Manter a segurança e integridade de nossos serviços. 4. Compartilhamento de Informações Não vendemos, alugamos ou compartilhamos suas informações pessoais com terceiros para fins de marketing sem o seu consentimento expresso. Podemos compartilhar suas informações apenas nas seguintes circunstâncias: Com prestadores de serviços terceirizados que nos ajudam a fornecer nossos serviços; Com autoridades governamentais, em conformidade com a lei; Em caso de fusão, aquisição ou venda de ativos, onde suas informações podem ser transferidas como parte do negócio. 5. Segurança de Dados Implementamos medidas de segurança técnicas, administrativas e físicas para proteger suas informações contra acesso não autorizado, uso indevido ou divulgação. No entanto, nenhuma transmissão de dados pela Internet ou sistema de armazenamento é totalmente seguro. 6. Seus Direitos Você tem direitos em relação às suas informações pessoais, incluindo o direito de acessar, corrigir, excluir ou limitar o uso de suas informações. Entre em contato conosco se precisar exercer esses direitos. 7. Alterações nesta Política Podemos atualizar esta Política de Privacidade periodicamente para refletir mudanças em nossas práticas de privacidade. Quaisquer alterações serão publicadas em nosso site e serão efetivas imediatamente após a publicação. 8. Contate-nos Se tiver dúvidas sobre esta Política de Privacidade ou sobre nossas práticas de privacidade, entre em contato conosco pelo e-mail spicemarket@gmail.com. Início Avaliações Política de Privacidade Termos de Uso SpiceMarket: sabor em cada grão!",
    "reviews": "SpiceMarket - Avalia es Sobre nós Vantagens Contato Avaliações +55-24-2168-8396 spicemarket@gmail.com Depoimentos dos nossos clientes As deliciosas especiarias do SpiceMarket fazem nossos clientes felizes. Experimente por si mesmo e comprove sua qualidade! Sobre nós O SpiceMarket é a sua fonte confiável para especiarias premium e ingredientes exóticos no Brasil. Nossa empresa tem uma longa história de fornecer produtos da mais alta qualidade, diretamente para sua cozinha. Nossa entrega rápida e eficiente garante que você obtenha seus temperos frescos no menor tempo possível. Além disso, nossa ampla gama de produtos e nossa reputação estabelecida no mercado brasileiro nos tornam uma escolha popular entre os chefs e amantes da culinária em todo o país. Depoimentos João Silva \"Desde que comecei a usar as especiarias do SpiceMarket, minha culinária nunca mais foi a mesma. Os sabores intensos e autênticos das especiarias trouxeram uma nova dimensão aos meus pratos. Recomendo especialmente o cardamomo e a pimenta caiena, que dão um toque único e irresistível!\" Pedro Oliveira \"As especiarias do SpiceMarket se tornaram essenciais na minha cozinha. A qualidade excepcional e a variedade de opções disponíveis me permitem experimentar novos sabores e criar pratos incríveis. Não consigo mais imaginar minha culinária sem elas!\" Carlos Santos \"O SpiceMarket é minha fonte confiável de especiarias autênticas e de alta qualidade. Suas misturas exclusivas e frescas sempre elevam o sabor dos meus pratos. Destaco especialmente o mix de temperos brasileiros, que adiciona um toque único e tropical às minhas receitas.\" Fernando Souza \"Minha experiência com o SpiceMarket tem sido nada menos que incrível. Além da excelente qualidade de suas especiarias, o serviço de entrega é rápido e confiável. Estou extremamente satisfeito com a variedade de produtos e o profissionalismo da equipe. Recomendo a todos os apaixonados por gastronomia!\" Explorando Nossas Especiarias Adentre o mundo vibrante e aromático do SpiceMarket, onde cada especiaria conta uma história única. Nossa vasta seleção é um tesouro de sabores, cores e aromas que refletem a rica diversidade culinária do Brasil e além. Desde os temperos tradicionais amados por gerações até as especiarias exóticas que despertam sua curiosidade, nosso assortimento oferece uma jornada sensorial incomparável. Descubra o sabor intenso do pimentão defumado, a fragrância floral do açafrão e a picância sutil da pimenta-negra. Além disso, estamos comprometidos em tornar sua experiência de compra ainda mais gratificante. Para pedidos acima de $100, oferecemos entrega gratuita diretamente à sua porta, permitindo que você desfrute de nossas delícias sem sair de casa. Seja você um chef experiente em busca de inspiração ou um amante da culinária explorando novos horizontes, o SpiceMarket é seu destino para encontrar os ingredientes perfeitos que transformarão suas receitas em obras-primas gastronômicas. Início Avaliações Política de Privacidade Termos de Uso SpiceMarket: sabor em cada grão!",
    "terms": "SpiceMarket - Condi es de uso Sobre nós Vantagens Contato Avaliações +55-24-2168-8396 spicemarket@gmail.com Termos de Uso 1. Introdução Bem-vindo aos Termos de Uso do SpiceMarket. Estes termos regem o uso do nosso site, aplicativo móvel ou outros serviços oferecidos por nós. Ao acessar ou usar nossos serviços, você concorda com estes termos e com nossa Política de Privacidade. 2. Uso do Serviço Você concorda em usar nossos serviços apenas para fins legais e de acordo com estes termos. Você não deve violar qualquer lei ou regulamento aplicável ao usar nossos serviços. Além disso, você concorda em não: Interferir ou interromper a operação normal de nossos serviços; Compartilhar informações falsas, enganosas ou prejudiciais; Usar nossos serviços para fins comerciais sem nossa permissão; Publicar conteúdo que viole os direitos de propriedade intelectual de terceiros; Enviar spam ou mensagens não solicitadas aos nossos usuários. 3. Conta do Usuário Para acessar determinadas áreas de nossos serviços, você pode ser solicitado a criar uma conta. Você é responsável por manter a segurança de sua conta e por qualquer atividade que ocorra nela. Informe-nos imediatamente sobre qualquer uso não autorizado de sua conta. 4. Propriedade Intelectual Todos os direitos de propriedade intelectual relacionados aos nossos serviços e ao conteúdo disponibilizado neles são de propriedade exclusiva do SpiceMarket ou de nossos licenciadores. Você concorda em não copiar, distribuir ou modificar qualquer parte de nossos serviços sem nossa autorização por escrito. 5. Limitação de Responsabilidade Em nenhuma circunstância seremos responsáveis por quaisquer danos diretos, indiretos, incidentais, especiais ou consequenciais decorrentes do uso de nossos serviços ou da incapacidade de usá-los, incluindo, mas não se limitando a, perda de lucros, interrupção de negócios ou perda de dados, mesmo que tenhamos sido avisados da possibilidade de tais danos. 6. Alterações nos Termos Podemos atualizar estes Termos de Uso periodicamente. Quaisquer alterações serão publicadas em nosso site e entrarão em vigor imediatamente após a publicação. Recomendamos que você revise regularmente os termos para estar ciente de quaisquer alterações. 7. Contate-nos Se tiver dúvidas sobre estes Termos de Uso, entre em contato conosco pelo e-mail spicemarket@gmail.com. Início Avaliações Política de Privacidade Termos de Uso SpiceMarket: sabor em cada grão!",
    "thanks": "SpiceMarket - Obrigado pela sua consulta! Obrigado pela sua consulta! Agradecemos por entrar em contato conosco. Sua busca por sabores autênticos e qualidade excepcional é o que nos impulsiona. Nossa equipe está trabalhando para atender sua solicitação com a máxima atenção. Em breve, você receberá uma resposta detalhada. Voltar à Página Inicial"
  },
  "date": "2024-05-28T09:49:27.210Z"
}