{
  "name": "winjackpotjivecasino",
  "pages": {
    "about": "Sobre o WinJackpotJiveCasino - Descubra Sua Experiência de Cassino Torneos Sobre Nosotros Club de Póker Contactos Torneos Sobre Nosotros Club de Póker Contactos Este sitio web utiliza cookies para mejorar su experiencia. Le informamos que utilizamos cookies para recopilar información sobre su comportamiento en el sitio web. Aceptar Bienvenido a WinJackpotJiveCasino La Mejor Experiencia de Casino Físico en Perú Contáctenos En WinJackpotJiveCasino, nos enorgullecemos de ofrecer una experiencia de juego inigualable. Nuestro casino Físico en Perú está diseñado para brindar emoción y entretenimiento a jugadores de todos los niveles. Desde los clásicos juegos de mesa hasta las tragamonedas más innovadoras, nuestro catálogo de juegos está repleto de opciones emocionantes para todos los gustos. Nos aseguramos de que cada jugador encuentre algo que le apasione. Nuestro equipo está comprometido con la excelencia, ofreciendo un servicio al cliente de primera clase y garantizando un entorno de juego seguro y justo. Valoramos la confianza de nuestros jugadores y trabajamos incansablemente para mantenerla. Únete a nosotros hoy y descubre por qué WinJackpotJiveCasino es el destino favorito para los entusiastas del casino Físico en Perú. ¡La suerte te espera! Este sitio web está destinado únicamente a personas mayores de 18 años. Al ingresar, confirma que tiene al menos 18 años. Sí No Sobre Nosotros Nuestra Historia WinJackpotJiveCasino se fundó con la misión de ofrecer la mejor experiencia de casino Físico en Perú. Desde nuestros inicios, hemos crecido para convertirnos en uno de los destinos más populares para los entusiastas de los juegos de azar. Visítanos Hoy Nuestra Misión En WinJackpotJiveCasino, nuestra misión es proporcionar un entorno seguro, justo y emocionante para todos nuestros jugadores. Nos esforzamos por ofrecer una amplia variedad de juegos de alta calidad y un servicio al cliente excepcional. Contáctanos Un Destino de Entretenimiento En WinJackpotJiveCasino, ofrecemos una experiencia de juego sin igual. Con nuestras instalaciones de última generación y una atmósfera vibrante, garantizamos momentos inolvidables para todos nuestros visitantes. Visítanos Hoy Compromiso con la Excelencia Nuestro equipo está dedicado a proporcionar un servicio excepcional y garantizar que cada visita sea única. Desde los juegos hasta la hospitalidad, cada detalle está diseñado para tu disfrute. Contáctanos Contáctanos para Más Información ¿Tienes alguna pregunta o necesitas asistencia? Rellena el formulario y nuestro equipo se pondrá en contacto contigo lo antes posible. Acepto la política de privacidad Enviar winjackpotjivecasino Jirón Domingo Cueto 445,Lince 15073, Peru Conecta con nosotros +5116135000 winjackpotjivecasino@gmail.com Información del Cliente Términos y Condiciones Política de Privacidad Aviso Legal Este sitio web está diseñado para proporcionar servicios de juego. Por favor, juega responsablemente y solo si tienes 18 años o más. Para obtener más información y soporte, visita",
    "contacts": "Entre em Contato - Suporte ao Cliente e Perguntas - WinJackpotJiveCasino Torneos Sobre Nosotros Club de Póker Contactos Torneos Sobre Nosotros Club de Póker Contactos Este sitio web utiliza cookies para mejorar su experiencia. Le informamos que utilizamos cookies para recopilar información sobre su comportamiento en el sitio web. Aceptar Contáctanos Estamos Aquí para Ayudarte Enviar Mensaje En WinJackpotJiveCasino, valoramos a nuestros jugadores y nos comprometemos a ofrecer el mejor soporte posible. Si tienes alguna pregunta, comentario o necesitas asistencia, no dudes en ponerte en contacto con nosotros. Nuestro equipo de soporte está disponible las 24 horas del día, los 7 días de la semana, para asegurarnos de que tu experiencia de juego sea la mejor posible. Puedes comunicarte con nosotros a través del formulario de contacto, por correo electrónico o llamándonos directamente. Dirección: Jirón Domingo Cueto 445,Lince 15073, Peru Correo Electrónico: winjackpotjivecasino@gmail.com Teléfono: +5116135000 Estamos aquí para responder a todas tus preguntas y resolver cualquier problema que puedas tener. Gracias por elegir WinJackpotJiveCasino, ¡esperamos que disfrutes de tu tiempo con nosotros! Este sitio web está destinado únicamente a personas mayores de 18 años. Al ingresar, confirma que tiene al menos 18 años. Sí No Contáctanos para Más Información ¿Tienes alguna pregunta o necesitas asistencia? Rellena el formulario y nuestro equipo se pondrá en contacto contigo lo antes posible. Acepto la política de privacidad Enviar winjackpotjivecasino Jirón Domingo Cueto 445,Lince 15073, Peru Conecta con nosotros +5116135000 winjackpotjivecasino@gmail.com Información del Cliente Términos y Condiciones Política de Privacidad Aviso Legal Este sitio web está diseñado para proporcionar servicios de juego. Por favor, juega responsablemente y solo si tienes 18 años o más. Para obtener más información y soporte, visita",
    "disclaimer": "Aviso Legal e Termos de Uso - WinJackpotJiveCasino Torneos Sobre Nosotros Club de Póker Contactos Torneos Sobre Nosotros Club de Póker Contactos Este sitio web utiliza cookies para mejorar su experiencia. Le informamos que utilizamos cookies para recopilar información sobre su comportamiento en el sitio web. Aceptar Este sitio web está destinado únicamente a personas mayores de 18 años. Al ingresar, confirma que tiene al menos 18 años. Sí No Aviso Legal Acerteza da Información Aviso General La información proporcionada en este sitio web es solo para fines informativos y no constituye una declaración o recomendación oficial. No damos ninguna garantía de ningún tipo, explícita o implícita, sobre la precisión, exactitud, confiabilidad, adecuación o disponibilidad con respecto al sitio web o a los contenidos, productos, servicios o gráficos relacionados en él para cualquier finalidad. Cualquier confianza que usted coloque en esta información es su responsabilidad. En ningún caso será nosotros responsables de cualquier pérdida o daño, incluyendo sin embargo, pérdidas o daños indirectos o daños cualesquiera que se deben a la pérdida de datos o ganancias que se deben a su uso de este sitio web. A través de este sitio web, puede acceder a otros sitios web que no están bajo nuestro control. No tenemos control sobre el contenido, características y disponibilidad de estos sitios web. La inclusión de cualquier enlace no implica una recomendación o endoso de las opiniones o información expresada dentro de ellos. Aunque hacemos todos nuestros esfuerzos para mantener el sitio web en funcionamiento de manera suave, no somos responsables de cualquier indisponibilidad temporal del sitio web debido a problemas técnicos al margen de nuestro control. Aviso Legal No hay Relación de Abogado-Cliente El contenido de este sitio web solo es para fines informativos y no constituye consejo legal. Consulte siempre un abogado cualificado para obtener consejos legales sobre cualquier asunto. El contenido contenido en este sitio web se proporciona solo para fines informativos y no debe interpretarse como consejo legal en cualquier asunto. No damos ninguna garantía de ningún tipo, explícita o implícita, sobre la precisión, exactitud, confiabilidad, adecuación o disponibilidad con respecto al sitio web o a los contenidos, productos, servicios o gráficos relacionados en él para cualquier finalidad. No nos responsabilizamos por cualquier pérdida, daño o pérdida causada por errores, omisiones o información engañosa contenida aquí o por su visualización o uso. La transmisión y recepción de información en este sitio web no constituye una relación de abogado-cliente entre winjackpotjivecasino y el usuario o navegador. Aunque hacemos todos nuestros esfuerzos para mantener el sitio web en funcionamiento de manera suave, no somos responsables de cualquier indisponibilidad temporal del sitio web debido a problemas técnicos al margen de nuestro control. Aviso Financiero Consejo de Inversión El contenido de este sitio web es solo para fines informativos y no constituye consejo financiero. No damos consejos financieros, y nada escrito aquí no debe interpretarse como recomendación para adquirir, vender o mantener cualquier inversión o seguro o para seguir cualquier estrategia de inversión. Todos los inversimientos implican riesgos y el rendimiento de un seguro o producto financiero no garantiza resultados futuros o retornos. No recomendamos o endosamos cualquier información o producto financiero mencionado aquí, y nada aquí debe interpretarse como una recomendación para adquirir, vender o mantener cualquier inversión o seguro o para seguir cualquier estrategia de inversión. No representamos o garantizamos ninguna información sobre la completa, correcta, confiable, adecuada o disponible con respecto al sitio web o a los contenidos, productos, servicios o gráficos relacionados en él para cualquier finalidad. Es recomendable consultar a un consultor financiero o planificador financiero cualificado antes de tomar cualquier decisión de inversión. Aviso de Salud Consejo Médico La información proporcionada en este sitio web es solo para fines informativos y no constituye consejo médico, diagnóstico o tratamiento. Consulte siempre un médico o otro profesional de la salud cualificado con cualquier pregunta que tenga sobre una condición médica. No ignore el consejo médico o la demora en buscarlo simplemente porque de algo que leyó a usted leer en este sitio web. winjackpotjivecasino no recomienda o endosa ninguna información o producto médico, procedimiento, opinión o otra información mencionada en este sitio web. La confianza en la información proporcionada en este sitio web es su responsabilidad. winjackpotjivecasino no hace representaciones o garantías de ningún tipo, explícitas o implícitas, sobre la completa, correcta, confiable, adecuada o disponible con respecto al sitio web o a los contenidos, productos, servicios o gráficos relacionados en él para cualquier finalidad. Contáctanos para Más Información ¿Tienes alguna pregunta o necesitas asistencia? Rellena el formulario y nuestro equipo se pondrá en contacto contigo lo antes posible. Acepto la política de privacidad Enviar winjackpotjivecasino Jirón Domingo Cueto 445,Lince 15073, Peru Conecta con nosotros +5116135000 winjackpotjivecasino@gmail.com Información del Cliente Términos y Condiciones Política de Privacidad Aviso Legal Este sitio web está diseñado para proporcionar servicios de juego. Por favor, juega responsablemente y solo si tienes 18 años o más. Para obtener más información y soporte, visita",
    "index": "WinJackpotJiveCasino - Cassino com Jogos Emocionantes Torneos Sobre Nosotros Club de Póker Contactos Torneos Sobre Nosotros Club de Póker Contactos Este sitio web utiliza cookies para mejorar su experiencia. Le informamos que utilizamos cookies para recopilar información sobre su comportamiento en el sitio web. Aceptar Experimente el Casino Físico en Perú O melhor casino do Peru está aqui! Contáctenos WinJackpotJiveCasino es el destino perfecto para todos los entusiastas de los juegos de azar. Con una amplia variedad de juegos, desde tragamonedas hasta póker, ofrecemos una experiencia de casino inigualable. En WinJackpotJiveCasino, la seguridad y la satisfacción de nuestros jugadores son nuestra prioridad. Utilizamos tecnología de punta para garantizar que todas sus transacciones sean seguras y protegidas. Además, ofrecemos atractivos bonos y promociones para que su experiencia sea aún más emocionante. ¡No espere más y únase a la acción en WinJackpotJiveCasino hoy mismo! ¿Tiene preguntas? Nuestro equipo de soporte está disponible las 24 horas para ayudarle. Contáctenos a través de nuestro sitio web o redes sociales. Este sitio web está destinado únicamente a personas mayores de 18 años. Al ingresar, confirma que tiene al menos 18 años. Sí No ¡Vive la emoción del juego en WinJackpotJiveCasino! Descubre la mejor selección de juegos de casino Físico en Perútragamonedas de última generación hasta mesas de póker en vivo. Únete a nuestra comunidad y experimenta la emoción de ganar en grande. Jugar Ahora En WinJackpotJiveCasino, nos enorgullece ofrecer una experiencia de juego segura y justa. Todos nuestros juegos están auditados y certificados por organismos independientes para garantizar que cada giro de la ruleta y cada mano de póker sean completamente aleatorios y equitativos. Nuestro casino Físico en Perúuna variedad de bonos y promociones diseñadas para maximizar su diversión y sus oportunidades de ganar. Desde bonos de bienvenida hasta giros gratis y recompensas de lealtad, siempre hay algo emocionante para aprovechar. Además, nuestra plataforma es fácil de usar y accesible desde cualquier dispositivo, ya sea que prefiera jugar desde su computadora, tableta o teléfono móvil. La interfaz intuitiva y el diseño elegante hacen que encontrar y jugar sus juegos favoritos sea un placer. ¿Listo para comenzar? Regístrese hoy mismo y reciba un bono de bienvenida exclusivo. Y si necesita ayuda, nuestro equipo de soporte al cliente está disponible las 24 horas del día, los 7 días de la semana, para asistirle con cualquier pregunta o inquietud que pueda tener. Torneos Emocionantes en WinJackpotJiveCasino Participa en nuestros emocionantes torneos y compite contra otros jugadores para ganar increíbles premios. ¡Cada torneo ofrece una experiencia única y la oportunidad de llevarse grandes recompensas! Torneo de Tragamonedas Fecha: 5 de julio Premio: $10,000 Únete a nuestro torneo de tragamonedas y demuestra tu habilidad girando los rodillos. ¡Los premios en efectivo esperan por ti! Torneo de Póker Texas Hold'em Fecha: 12 de julio Premio: $25,000 Participa en nuestro torneo de póker Texas Hold'em y enfrenta a los mejores jugadores. ¡Asegúrate de tener la mejor mano y lleva a casa el gran premio! Torneo de Ruleta Fecha: 19 de julio Premio: $15,000 Gira la rueda de la fortuna en nuestro torneo de ruleta. ¡Con un poco de suerte, podrías ser el próximo gran ganador! No te pierdas la oportunidad de ser parte de la acción en WinJackpotJiveCasino. Inscríbete en nuestros torneos y vive la emoción del juego competitivo. Regístrate Ahora Delicias Culinarias en WinJackpotJiveCasino En WinJackpotJiveCasino, no solo nos enorgullecemos de nuestros juegos de casino, sino también de nuestra excelente oferta gastronómica. Disfruta de una variedad de platos exquisitos preparados por chefs de renombre. Desde aperitivos ligeros hasta cenas gourmet, nuestra selección de comidas está diseñada para satisfacer todos los gustos. Acompaña tu experiencia de juego con una experiencia culinaria de primera clase. Reservar Mesa Bebidas Exclusivas Nuestro bar ofrece una selección exclusiva de bebidas para acompañar tu velada en el casino. Disfruta de cócteles artesanales, vinos finos y una amplia variedad de cervezas y licores. Nuestros bartenders están listos para sorprenderte con sus creaciones únicas. Ya sea que prefieras un clásico o algo nuevo y emocionante, tenemos la bebida perfecta para ti. Ver Menú de Bebidas ¡Únete a la Diversión en WinJackpotJiveCasino! ¡Bonos y Promociones Exclusivas Esperan por Ti! En WinJackpotJiveCasino, siempre tenemos algo especial para nuestros jugadores. Aprovecha nuestras ofertas exclusivas y mejora tu experiencia de juego con bonos increíbles. Desde bonos de bienvenida hasta promociones semanales y mensuales, hay algo para todos. No te pierdas las oportunidades de ganar más y jugar más. Reclamar Bonos Sobre Nosotros Nuestra Historia WinJackpotJiveCasino se fundó con la misión de ofrecer la mejor experiencia de casino Físico en Desde nuestros inicios, hemos crecido para convertirnos en uno de los destinos más populares para los entusiastas de los juegos de azar. Visítanos Hoy Nuestra Misión En WinJackpotJiveCasino, nuestra misión es proporcionar un entorno seguro, justo y emocionante para todos nuestros jugadores. Nos esforzamos por ofrecer una amplia variedad de juegos de alta calidad y un servicio al cliente excepcional. Contáctanos Nuestros Juegos Populares En WinJackpotJiveCasino, ofrecemos una variedad inigualable de juegos para satisfacer todos los gustos. Desde juegos de cartas clásicos hasta tragamonedas modernas, tenemos algo para todos. Póker Únete a nuestras mesas de póker y demuestra tu habilidad contra jugadores de todo el mundo. ¡Las mejores manos ganan! Jugar Ahora Blackjack Prueba tu suerte y estrategia en nuestras mesas de blackjack. ¡El objetivo es llegar a 21 sin pasarse! Jugar Ahora Tragamonedas Gira los rodillos de nuestras tragamonedas y descubre emocionantes premios y bonos. ¡La suerte está de tu lado! Jugar Ahora Ruleta Disfruta de la emoción de la ruleta y apuesta a tu número o color favorito. ¡Gira la rueda y gana en grande! Jugar Ahora ¡Donde la Fortuna Sonríe! En WinJackpotJiveCasino, la suerte está siempre a tu favor. Únete a nosotros y experimenta la emoción del juego como nunca antes. Con cada giro y cada carta, la posibilidad de ganar en grande te espera. Comienza a Jugar Contáctanos para Más Información ¿Tienes alguna pregunta o necesitas asistencia? Rellena el formulario y nuestro equipo se pondrá en contacto contigo lo antes posible. Acepto la política de privacidad Enviar winjackpotjivecasino Jirón Domingo Cueto 445,Lince 15073, Peru Conecta con nosotros +5116135000 winjackpotjivecasino@gmail.com Información del Cliente Términos y Condiciones Política de Privacidad Aviso Legal Este sitio web está diseñado para proporcionar servicios de juego. Por favor, juega responsablemente y solo si tienes 18 años o más. Para obtener más información y soporte, visita",
    "poker-club": "Poker-Clube no WinJackpotJiveCasino Torneos Sobre Nosotros Club de Póker Contactos Torneos Sobre Nosotros Club de Póker Contactos Este sitio web utiliza cookies para mejorar su experiencia. Le informamos que utilizamos cookies para recopilar información sobre su comportamiento en el sitio web. Aceptar Bienvenido al Club de Póker Únete a Nuestra Comunidad Exclusiva de Póker Contáctenos En WinJackpotJiveCasino, nuestro Club de Póker está diseñado para los verdaderos entusiastas del juego. Ofrecemos un entorno exclusivo y sofisticado donde puedes poner a prueba tus habilidades y disfrutar de la emoción del póker con otros jugadores apasionados. Nuestro club organiza torneos regulares con increíbles premios en efectivo, así como eventos especiales donde puedes competir contra los mejores jugadores. Ya seas un profesional experimentado o un aficionado, encontrarás una mesa adecuada para tu nivel. Los miembros del Club de Póker también disfrutan de beneficios exclusivos, como acceso a salas privadas, promociones especiales y atención personalizada de nuestro equipo de soporte. Queremos asegurarnos de que cada miembro tenga una experiencia única y gratificante. Para unirte a nuestro Club de Póker, simplemente completa el formulario de inscripción y nuestro equipo se pondrá en contacto contigo para proporcionarte todos los detalles. ¡No pierdas la oportunidad de ser parte de la comunidad de póker más emocionante! Este sitio web está destinado únicamente a personas mayores de 18 años. Al ingresar, confirma que tiene al menos 18 años. Sí No Únete al Club de Póker Hoy Experimenta la emoción del póker en un entorno exclusivo y competitivo. ¡Regístrate ahora y comienza a jugar! Jugar Ahora Delicias para los Miembros del Club Nuestro Club de Póker no solo ofrece grandes juegos, sino también una experiencia culinaria de primera clase. Disfruta de una variedad de platillos exquisitos mientras juegas. Desde bocadillos gourmet hasta comidas completas, nuestro menú está diseñado para satisfacer todos tus antojos mientras te concentras en tu juego. Explora el Menú Bebidas Exclusivas para los Jugadores Nuestro bar ofrece una selección exclusiva de bebidas premium. Relájate y disfruta de tu cóctel favorito entre jugadas. Ya sea que prefieras un whisky añejo, un vino fino o un refrescante cóctel, nuestro equipo de bartenders está listo para servirte. Conoce Nuestras Bebidas ¿Listo para Ganar en Grande? No esperes más. Únete a nuestro Club de Póker y demuestra tus habilidades. ¡Las grandes recompensas te esperan! Jugar Ahora Contáctanos para Más Información ¿Tienes alguna pregunta o necesitas asistencia? Rellena el formulario y nuestro equipo se pondrá en contacto contigo lo antes posible. Acepto la política de privacidad Enviar winjackpotjivecasino Jirón Domingo Cueto 445,Lince 15073, Peru Conecta con nosotros +5116135000 winjackpotjivecasino@gmail.com Información del Cliente Términos y Condiciones Política de Privacidad Aviso Legal Este sitio web está diseñado para proporcionar servicios de juego. Por favor, juega responsablemente y solo si tienes 18 años o más. Para obtener más información y soporte, visita",
    "privacy": "winjackpotjivecasino Torneos Sobre Nosotros Club de Póker Contactos Torneos Sobre Nosotros Club de Póker Contactos Este sitio web utiliza cookies para mejorar su experiencia. Le informamos que utilizamos cookies para recopilar información sobre su comportamiento en el sitio web. Aceptar Este sitio web está destinado únicamente a personas mayores de 18 años. Al ingresar, confirma que tiene al menos 18 años. Sí No Политика конфиденциальности Введение Общий взгляд Ваша конфиденциальность для нас очень важна. Наша политика будет уважать вашу конфиденциальность в отношении любых личных данных, которые можем собрать от вас на нашем сайте, и на других сайтах, которые мы управляем и эксплуатиров в мире. Мы собираем личные данные только в тех случаях, когда это абсолютно необходимо. Мы собираем личные данные только по законным и честным средствам. Кроме того, мы информируем вас о том, что собираем, и как это будет использовано. Мы храним собранные данные только на время, необходимое для предоставления запрашиваемого сервиса. Собранные данные хранятся нами в коммерческих условиях, чтобы предотвратить потерю и разбой, а также чтобы предотвратить неавторизованное доступ, разглашение, копирование, редактирование или модификацию. Мы не будем делить личные данные, идентифицирующие вас, с третьими лицами, за исключением случаев, когда это требуют законы. Сбор данных Типы собранных данных Мы собираем личные данные, которые вы нам предоставите добровольно, когда взаимодействуете с нашими сервисами, такие как имя, адрес электронной почты, номер телефона и т.д. Тем самым неличными данными, которые мы собираем, являются cookie или другие технологии отслеживания, когда вы посещаете наш сайт. Использование данных Как мы используем ваши данные Собранные данные используются для улучшения содержания и функциональности нашего сайта, а также для предоставления вам сервиса клиента. Мы можем использовать ваши данные для персонализации вашей опыт и для того, чтобы мы могли предложить вам те контент и продукты, которые вы больше всего интересуют. Ваше личные данные, будь то общественное или частное, не будут продаваться, обмениваться, передаваться или предоставляться какому-либо другому предприятию по какому-либо основанию, кроме случаев, когда это предъявлено для предоставления запрашиваемого сервиса. Безопасность данных Меры безопасности Мы реализовываем разнообразные меры безопасности, чтобы гарантировать безопасность вашей личной информации, когда вы нам предоставляете информацию, отправляете запрос или доступяете к вашим личным данным. Мы предлагаем использование безопасного сервера. Всё конфиденциальное, что вы предоставляете, отправляете через технологию SSL и, после того, как это криптографируется, передается на наши банки данных, чтобы быть доступным только в указанных выше обстоятельствах. Contáctanos para Más Información ¿Tienes alguna pregunta o necesitas asistencia? Rellena el formulario y nuestro equipo se pondrá en contacto contigo lo antes posible. Acepto la política de privacidad Enviar winjackpotjivecasino Jirón Domingo Cueto 445,Lince 15073, Peru Conecta con nosotros +5116135000 winjackpotjivecasino@gmail.com Información del Cliente Términos y Condiciones Política de Privacidad Aviso Legal Este sitio web está diseñado para proporcionar servicios de juego. Por favor, juega responsablemente y solo si tienes 18 años o más. Para obtener más información y soporte, visita",
    "terms": "Termos e Condições - WinJackpotJiveCasino Torneos Sobre Nosotros Club de Póker Contactos Torneos Sobre Nosotros Club de Póker Contactos Este sitio web utiliza cookies para mejorar su experiencia. Le informamos que utilizamos cookies para recopilar información sobre su comportamiento en el sitio web. Aceptar Este sitio web está destinado únicamente a personas mayores de 18 años. Al ingresar, confirma que tiene al menos 18 años. Sí No Términos y Condiciones 1. Introducción Concordancia de los Términos Estos Términos y Condiciones regulan el uso de este sitio web; al utilizar este sitio web, aceptas los Términos y Condiciones en su totalidad. Si no aceptas estos Términos y Condiciones o cualquier parte de ellos, no debes utilizar este sitio web. 2. Derechos de Propiedad Intelectual Propiedad de los Contenidos A menos que se indique lo contrario, nosotros o nuestros licenciantes poseemos los derechos de propiedad intelectual en el sitio web y en el contenido presente en el sitio web. Subjetos a la licencia que se indica a continuación, todos estos derechos de propiedad intelectual están reservados. 3. Uso del Sitio Web Restricciones de Uso No debes utilizar este sitio web de manera que cause, o pueda causar, daños al sitio web o comprometer la disponibilidad o accesibilidad del sitio web; o de cualquier otra forma que sea ilegal, fraudulenta o perjudicial. 4. Limitaciones de Responsabilidad Exención de Responsabilidad La información contenida en este sitio web es solo para fines generales. La información se proporciona por [Nombre de tu Empresa] y, aunque nos esforzamos por mantener la información actualizada y precisa, no hacemos representaciones o garantías de ningún tipo, explícitas o implícitas, sobre la completitud, precisión, confiabilidad, adecuación o disponibilidad con respecto al sitio web o a la información, productos, servicios o gráficos relacionados que se encuentran en el sitio web para cualquier propósito. Cualquier confianza que deposites en esta información corresponde únicamente a tu propio riesgo. 5. Ley Aplicable Jurisdicción Estos Términos y Condiciones serán regidos y interpretados de acuerdo con las leyes, y cualquier disputa relacionada con estos Términos y Condiciones estarán sujeta a la jurisdicción exclusiva de los tribunales. Contáctanos para Más Información ¿Tienes alguna pregunta o necesitas asistencia? Rellena el formulario y nuestro equipo se pondrá en contacto contigo lo antes posible. Acepto la política de privacidad Enviar winjackpotjivecasino Jirón Domingo Cueto 445,Lince 15073, Peru Conecta con nosotros +5116135000 winjackpotjivecasino@gmail.com Información del Cliente Términos y Condiciones Política de Privacidad Aviso Legal Este sitio web está diseñado para proporcionar servicios de juego. Por favor, juega responsablemente y solo si tienes 18 años o más. Para obtener más información y soporte, visita",
    "thank_you": "Agradecemos seu Contato - WinJackpotJiveCasino Torneos Sobre Nosotros Club de Póker Contactos Torneos Sobre Nosotros Club de Póker Contactos Este sitio web utiliza cookies para mejorar su experiencia. Le informamos que utilizamos cookies para recopilar información sobre su comportamiento en el sitio web. Aceptar Este sitio web está destinado únicamente a personas mayores de 18 años. Al ingresar, confirma que tiene al menos 18 años. Sí No ¡Gracias por ponerte en contacto! Agradecimiento Recibimos su mensaje Agradecemos por ponerse en contacto con nosotros. Su mensaje ha sido recibido con éxito y nos pondremos en contacto con usted en la brevedad. Información de contacto Tiempo de respuesta Nuestro objetivo es responder a todas las mensajes en un plazo máximo de 24 horas hábiles. Mantente en contacto Mantenga un ojo en su bandeja de entrada. Le enviaremos una respuesta al correo electrónico proporcionado. Política de Privacidad Seguridad y privacidad Respetamos su privacidad. Toda la información proporcionada será tratada de manera confidencial de acuerdo con nuestra Política de Privacidad. Uso de Información La información proporcionada será utilizada únicamente para responder a su consulta. No compartiremos sus datos con terceros sin su autorización. Retorno a la página de inicio Vuelva a visitar nuestro sitio web Estamos emocionados por atender a sus necesidades. Mientras tanto, esté libre de explorar otras partes de nuestro sitio web y descubra todo lo que tenemos para ofrecerle. Contáctanos para Más Información ¿Tienes alguna pregunta o necesitas asistencia? Rellena el formulario y nuestro equipo se pondrá en contacto contigo lo antes posible. Acepto la política de privacidad Enviar winjackpotjivecasino Jirón Domingo Cueto 445,Lince 15073, Peru Conecta con nosotros +5116135000 winjackpotjivecasino@gmail.com Información del Cliente Términos y Condiciones Política de Privacidad Aviso Legal Este sitio web está diseñado para proporcionar servicios de juego. Por favor, juega responsablemente y solo si tienes 18 años o más. Para obtener más información y soporte, visita",
    "tournamet": "Torneios no WinJackpotJiveCasino - Competições de Cassino Torneos Sobre Nosotros Club de Póker Contactos Torneos Sobre Nosotros Club de Póker Contactos Este sitio web utiliza cookies para mejorar su experiencia. Le informamos que utilizamos cookies para recopilar información sobre su comportamiento en el sitio web. Aceptar Torneos Emocionantes Participa y Gana Grandes Premios Contáctenos En WinJackpotJiveCasino, nos enorgullece organizar los torneos más emocionantes y competitivos. Nuestros torneos están diseñados para jugadores de todos los niveles, desde principiantes hasta profesionales experimentados. Ofrecemos una amplia variedad de torneos, incluidos torneos de tragamonedas, torneos de póker y competiciones de blackjack. Cada torneo ofrece la oportunidad de ganar premios impresionantes y demostrar tus habilidades frente a otros jugadores. Para participar, simplemente regístrate en nuestro sitio web y selecciona el torneo que más te interese. Nuestro calendario de torneos se actualiza regularmente para que siempre tengas algo emocionante en lo que participar. No pierdas la oportunidad de unirte a la acción. ¡Inscríbete hoy mismo y prepárate para ganar en grande en WinJackpotJiveCasino! Este sitio web está destinado únicamente a personas mayores de 18 años. Al ingresar, confirma que tiene al menos 18 años. Sí No Torneos Emocionantes en WinJackpotJiveCasino Participa en nuestros emocionantes torneos y compite contra otros jugadores para ganar increíbles premios. ¡Cada torneo ofrece una experiencia única y la oportunidad de llevarse grandes recompensas! Torneo de Tragamonedas Fecha: 5 de julio Premio: $10,000 Únete a nuestro torneo de tragamonedas y demuestra tu habilidad girando los rodillos. ¡Los premios en efectivo esperan por ti! Torneo de Póker Texas Hold'em Fecha: 12 de julio Premio: $25,000 Participa en nuestro torneo de póker Texas Hold'em y enfrenta a los mejores jugadores. ¡Asegúrate de tener la mejor mano y lleva a casa el gran premio! Torneo de Blackjack Fecha: 19 de julio Premio: $15,000 Desafía a otros jugadores en nuestro torneo de blackjack. ¡Con estrategia y un poco de suerte, podrías ser el próximo campeón! Torneo de Baccarat Fecha: 26 de julio Premio: $20,000 Prueba tu suerte y habilidad en nuestro torneo de baccarat. ¡Gana a lo grande y disfruta de la emoción del juego! Torneo de Ruleta Fecha: 2 de agosto Premio: $15,000 Gira la rueda de la fortuna en nuestro torneo de ruleta. ¡Con un poco de suerte, podrías ser el próximo gran ganador! Torneo de Póker Omaha Fecha: 9 de agosto Premio: $30,000 Si eres un fanático del póker Omaha, este torneo es para ti. ¡Compite contra otros jugadores y lleva tu estrategia al límite! Torneo de Tragamonedas Progresivas Fecha: 16 de agosto Premio: Jackpot Progresivo Participa en nuestro torneo de tragamonedas progresivas y juega por el premio mayor. ¡El jackpot podría ser tuyo! Torneo de Póker de 5 Cartas Fecha: 23 de agosto Premio: $12,000 Demuestra tus habilidades en el póker de 5 cartas y compite por el premio en efectivo. ¡Cada mano cuenta! Torneo de Video Póker Fecha: 30 de agosto Premio: $8,000 Únete a nuestro torneo de video póker y juega para ganar. ¡Las combinaciones ganadoras te esperan! No te pierdas la oportunidad de ser parte de la acción en WinJackpotJiveCasino. Inscríbete en nuestros torneos y vive la emoción del juego competitivo. Regístrate Ahora Bienvenido a WinJackpotJiveCasino ¡Descubre nuestros emocionantes juegos y premios! Sumérgete en la emoción de los juegos de casino más populares, desde tragamonedas hasta póker. Disfruta de bonos exclusivos y ofertas especiales solo para nuestros jugadores. Reclama tus Bonos Ahora Contáctanos para Más Información ¿Tienes alguna pregunta o necesitas asistencia? Rellena el formulario y nuestro equipo se pondrá en contacto contigo lo antes posible. Acepto la política de privacidad Enviar winjackpotjivecasino Jirón Domingo Cueto 445,Lince 15073, Peru Conecta con nosotros +5116135000 winjackpotjivecasino@gmail.com Información del Cliente Términos y Condiciones Política de Privacidad Aviso Legal Este sitio web está diseñado para proporcionar servicios de juego. Por favor, juega responsablemente y solo si tienes 18 años o más. Para obtener más información y soporte, visita"
  },
  "date": "2024-07-02T15:06:00.880Z"
}